pycps/__init__.py
pycps/get_data.py
pycps/py.typed
pycpsdata-1.0.1.dist-info/LICENSE
pycpsdata-1.0.1.dist-info/METADATA
pycpsdata-1.0.1.dist-info/WHEEL
pycpsdata-1.0.1.dist-info/top_level.txt
pycpsdata-1.0.1.dist-info/RECORD
