Metadata-Version: 2.1
Name: pycpsdata
Version: 1.0.1
Summary: Load CPS microdata into a pandas DataFrame using the Census API.
Home-page: https://github.com/matt-saenz/PyCPS
Author: Matt Saenz
Author-email: mattsaenz165@gmail.com
Project-URL: Bug Reports, https://github.com/matt-saenz/PyCPS/issues
Project-URL: Source, https://github.com/matt-saenz/PyCPS
Keywords: pycpsdata,pycps,cps,current population survey,microdata,census bureau
Classifier: Intended Audience :: Science/Research
Classifier: License :: OSI Approved :: MIT License
Classifier: Natural Language :: English
Classifier: Operating System :: OS Independent
Classifier: Programming Language :: Python
Classifier: Programming Language :: Python :: 3
Classifier: Programming Language :: Python :: 3 :: Only
Classifier: Programming Language :: Python :: 3.10
Classifier: Programming Language :: Python :: 3.11
Requires-Python: <4,>=3.10
License-File: LICENSE
Requires-Dist: pandas >=1.5.0
Requires-Dist: requests >=2.28.1
